stackdio/__init__.py
stackdio/cli/__init__.py
stackdio/cli/utils.py
stackdio/cli/blueprints/__init__.py
stackdio/cli/blueprints/generator.py
stackdio/cli/mixins/__init__.py
stackdio/cli/mixins/blueprints.py
stackdio/cli/mixins/formulas.py
stackdio/cli/mixins/stacks.py
stackdio/client/__init__.py
stackdio/client/account.py
stackdio/client/blueprint.py
stackdio/client/compat.py
stackdio/client/config.py
stackdio/client/exceptions.py
stackdio/client/formula.py
stackdio/client/http.py
stackdio/client/image.py
stackdio/client/region.py
stackdio/client/settings.py
stackdio/client/stack.py
stackdio/client/version.py
stackdio-0.7.3.dist-info/DESCRIPTION.rst
stackdio-0.7.3.dist-info/METADATA
stackdio-0.7.3.dist-info/RECORD
stackdio-0.7.3.dist-info/WHEEL
stackdio-0.7.3.dist-info/entry_points.txt
stackdio-0.7.3.dist-info/metadata.json
stackdio-0.7.3.dist-info/top_level.txt
