Metadata-Version: 2.0
Name: stackdio
Version: 0.7.3
Summary: A cloud deployment, automation, and orchestration platform for everyone.
Home-page: http://stackd.io
Author: Digital Reasoning Systems, Inc.
Author-email: info@stackd.io
License: Apache 2.0
Platform: UNKNOWN
Classifier: Development Status :: 4 - Beta
Classifier: Environment :: Web Environment
Classifier: Intended Audience :: Developers
Classifier: Intended Audience :: Information Technology
Classifier: Intended Audience :: System Administrators
Classifier: License :: OSI Approved :: Apache Software License
Classifier: Programming Language :: Python
Classifier: Programming Language :: Python :: 2
Classifier: Programming Language :: Python :: 2.7
Classifier: Programming Language :: Python :: 3
Classifier: Programming Language :: Python :: 3.3
Classifier: Programming Language :: Python :: 3.4
Classifier: Topic :: System :: Clustering
Classifier: Topic :: System :: Distributed Computing
Requires-Dist: Jinja2 (>=2.7)
Requires-Dist: PyYAML (>=3.10)
Requires-Dist: click (>=6.0,<7.0)
Requires-Dist: click-shell (>=0.4)
Requires-Dist: colorama (>=0.3,<0.4)
Requires-Dist: keyring (==3.7)
Requires-Dist: requests (>=2.4.0)
Requires-Dist: simplejson (==3.4.0)
Provides-Extra: testing
Requires-Dist: coveralls; extra == 'testing'
Requires-Dist: pep8; extra == 'testing'
Requires-Dist: pylint (<=1.2.0); extra == 'testing'
